demo/__init__.py
demo/transport_demo.py
wedpr_python_gateway_sdk/__init__.py
wedpr_python_gateway_sdk/libs/__init__.py
wedpr_python_gateway_sdk/libs/_wedpr_python_transport.py
wedpr_python_gateway_sdk/libs/libwedpr_python_transport.dylib
wedpr_python_gateway_sdk/libs/libwedpr_python_transport.so
wedpr_python_gateway_sdk/transport/__init__.py
wedpr_python_gateway_sdk/transport/api/__init__.py
wedpr_python_gateway_sdk/transport/api/message_api.py
wedpr_python_gateway_sdk/transport/api/transport_api.py
wedpr_python_gateway_sdk/transport/generated/__init__.py
wedpr_python_gateway_sdk/transport/generated/wedpr_python_transport.py
wedpr_python_gateway_sdk/transport/impl/__init__.py
wedpr_python_gateway_sdk/transport/impl/message_factory.py
wedpr_python_gateway_sdk/transport/impl/message_impl.py
wedpr_python_gateway_sdk/transport/impl/route_info_builder.py
wedpr_python_gateway_sdk/transport/impl/transport.py
wedpr_python_gateway_sdk/transport/impl/transport_config.py
wedpr_python_gateway_sdk/transport/impl/transport_loader.py
wedpr_python_gateway_sdk/utils/__init__.py
wedpr_python_gateway_sdk/utils/base_object.py
wedpr_python_gateway_sdk/utils/lib_loader.py
wedpr_python_gateway_sdk/utils/utils.py
wedpr_python_gateway_sdk-3.0.0.post20241019.dist-info/METADATA
wedpr_python_gateway_sdk-3.0.0.post20241019.dist-info/WHEEL
wedpr_python_gateway_sdk-3.0.0.post20241019.dist-info/top_level.txt
wedpr_python_gateway_sdk-3.0.0.post20241019.dist-info/RECORD
